{
  "id": "xiaomi-u0-robot-data-factory-ko",
  "title": "오픈소스 월드모델로 로봇 학습 데이터 생성이 82배 빨라졌다",
  "path": "blog/xiaomi-u0-robot-data-factory/ko/",
  "date": "2026-07-18",
  "category": "tech",
  "published": true,
  "featured": false,
  "description": "샤오미가 로봇 월드모델 U0를 오픈소스로 공개했다. 1024×1024 이미지 생성을 450초에서 5.4초로 82배 줄이고 실제 로봇 궤적을 재촬영 없이 새 환경으로 이식한다. 물량이 늘어난 다음 합성 데이터의 충실도와 계보를 누가 검증하느냐는 새 병목을 짚는다.",
  "image": "blog/xiaomi-u0-robot-data-factory/ko/image/index.png",
  "language": "ko",
  "tags": ["로봇 데이터", "월드모델", "합성 데이터", "Physical AI", "데이터 거버넌스", "Xiaomi Robotics-U0", "오픈소스", "데이터 계보"],
  "provenance": {
    "mode": "unattended",
    "humanReviewed": false,
    "trigger": {
      "source": "scheduled",
      "actor": "scheduler(auto-seq)",
      "at": "2026-07-17T20:02:48.624Z"
    },
    "gates": [
      {
        "phase": "write-ko",
        "resolution": "auto_passed",
        "by": "engine",
        "at": "2026-07-17T20:13:01.086Z"
      }
    ],
    "engine": {
      "runId": "run-1784318568624-y9k9bp",
      "version": "0.1.0"
    },
    "recordedAt": "2026-07-17T20:44:25.007Z"
  }
}
